{
  "id": "L-B2-GOETHE-004-T3",
  "level": "B2",
  "teil": 3,
  "teil_name": "Diskussion mehrere Personen",
  "task_type": "mc_abc",
  "topic": "Praktikumserfahrungen im Studium",
  "audio_file": "/audio/listening/B2/Teil3-Diskussion-mehrere-Personen/L-B2-GOETHE-004-T3.mp3",
  "metadata": {
    "generated_at": "2026-03-19T10:04:11.226361",
    "version": 2,
    "gespraech_count": 6,
    "source_script": "data/scripts/B2/Teil3-Diskussion-mehrere-Personen/L-B2-GOETHE-004-T3.json",
    "regenerated_at": "2026-03-20T07:45:14.530Z"
  },
  "questions": [
    {
      "id": "Q1",
      "gespraech": 1,
      "type": "mc_abc",
      "question": "Worum geht es im Gespräch 1?",
      "options": {
        "a": "Einkaufen und Geld",
        "b": "Bildung und Schule",
        "c": "Arbeit und Beruf"
      },
      "answer": "a",
      "points": 1,
      "explanation": {
        "de": "Man hört: \"Einkaufen und Geld\".",
        "vi": "",
        "key_evidence": "Einkaufen und Geld",
        "key_vocabulary": []
      }
    },
    {
      "id": "Q2",
      "gespraech": 1,
      "type": "mc_abc",
      "question": "Wie heißt eine Person im Gespräch 1?",
      "options": {
        "a": "Thomas",
        "b": "Andreas",
        "c": "Wolf"
      },
      "answer": "c",
      "points": 1,
      "explanation": {
        "de": "Man hört: \"Wolf\".",
        "vi": "",
        "key_evidence": "Wolf",
        "key_vocabulary": [
          {
            "w": "heißen",
            "m": "to be called"
          }
        ]
      }
    },
    {
      "id": "Q3",
      "gespraech": 1,
      "type": "mc_abc",
      "question": "Woher kommt die Person (Gespräch 1)?",
      "options": {
        "a": "Geld",
        "b": "Leipzig",
        "c": "Köln"
      },
      "answer": "a",
      "points": 1,
      "explanation": {
        "de": "Man hört: \"Geld\".",
        "vi": "",
        "key_evidence": "Geld",
        "key_vocabulary": [
          {
            "w": "kommen aus",
            "m": "to come from"
          }
        ]
      }
    },
    {
      "id": "Q4",
      "gespraech": 1,
      "type": "mc_abc",
      "question": "Was macht die Person beruflich (Gespräch 1)?",
      "options": {
        "a": "Praktikant",
        "b": "Arzt",
        "c": "Studentin"
      },
      "answer": "a",
      "points": 1,
      "explanation": {
        "de": "Man hört: \"Praktikant\".",
        "vi": "",
        "key_evidence": "Praktikant",
        "key_vocabulary": [
          {
            "w": "Praktikant",
            "m": "Praktikant"
          }
        ]
      }
    }
  ],
  "scoring": {
    "total_points": 4,
    "pass_threshold": 3,
    "grading": [
      {
        "range": [
          4,
          4
        ],
        "label": "Ausgezeichnet!",
        "emoji": "⭐⭐⭐"
      },
      {
        "range": [
          3,
          3
        ],
        "label": "Sehr gut!",
        "emoji": "⭐⭐"
      },
      {
        "range": [
          2,
          2
        ],
        "label": "Gut!",
        "emoji": "⭐"
      },
      {
        "range": [
          0,
          1
        ],
        "label": "Noch üben!",
        "emoji": "📝"
      }
    ]
  }
}