{
  "id": "L-A1-GOETHE-008-T2",
  "level": "A1",
  "teil": 2,
  "teil_name": "Durchsagen und Ansagen",
  "task_type": "richtig_falsch",
  "topic": "Wochenendplan besprechen",
  "audio_file": "/audio/listening/A1/Teil2-Durchsagen-und-Ansagen/L-A1-GOETHE-008-T2.mp3",
  "metadata": {
    "generated_at": "2026-03-19T10:04:11.075048",
    "version": 6,
    "gespraech_count": 4,
    "source_script": "data/scripts/A1/Teil2-Durchsagen-und-Ansagen/L-A1-GOETHE-008-T2.json",
    "regenerated_at": "2026-03-20T07:53:59.185Z"
  },
  "questions": [
    {
      "id": "Q1",
      "gespraech": 1,
      "type": "richtig_falsch",
      "question": "Das Stadtfest beginnt um 23 Uhr.",
      "answer": "falsch",
      "points": 1,
      "explanation": {
        "de": "Der Ansager sagt, dass das Fest um elf Uhr beginnt und um dreiundzwanzig Uhr endet.",
        "vi": "Người thông báo nói rằng lễ hội bắt đầu lúc 11 giờ và kết thúc lúc 23 giờ.",
        "key_evidence": "Das Fest beginnt um elf Uhr. Das Fest endet um dreiundzwanzig Uhr.",
        "key_vocabulary": []
      }
    },
    {
      "id": "Q2",
      "gespraech": 2,
      "type": "richtig_falsch",
      "question": "Der Volkslauf findet im Stadtpark statt.",
      "answer": "richtig",
      "points": 1,
      "explanation": {
        "de": "Der Ansager sagt, dass der Volkslauf im Stadtpark stattfindet.",
        "vi": "Người thông báo nói rằng cuộc chạy bộ cộng đồng diễn ra ở công viên thành phố.",
        "key_evidence": "Am Sonntag gibt es einen Volkslauf im Stadtpark.",
        "key_vocabulary": []
      }
    },
    {
      "id": "Q3",
      "gespraech": 3,
      "type": "richtig_falsch",
      "question": "Der Wochenmarkt ist am Sonntag geöffnet.",
      "answer": "falsch",
      "points": 1,
      "explanation": {
        "de": "Der Ansager sagt, dass der Markt am Sonntag geschlossen ist.",
        "vi": "Người thông báo nói rằng chợ đóng cửa vào Chủ Nhật.",
        "key_evidence": "Am Sonntag ist der Markt geschlossen.",
        "key_vocabulary": []
      }
    },
    {
      "id": "Q4",
      "gespraech": 4,
      "type": "richtig_falsch",
      "question": "Eltern zahlen für das Kinderprogramm zwei Euro.",
      "answer": "falsch",
      "points": 1,
      "explanation": {
        "de": "Der Ansager sagt, dass der Eintritt zwei Euro pro Kind kostet, aber Eltern sind frei.",
        "vi": "Người thông báo nói rằng vé vào cửa là hai Euro cho mỗi trẻ em, nhưng cha mẹ được miễn phí.",
        "key_evidence": "Der Eintritt kostet zwei Euro pro Kind. Eltern sind frei.",
        "key_vocabulary": []
      }
    }
  ],
  "scoring": {
    "total_points": 4,
    "pass_threshold": 3,
    "grading": [
      {
        "range": [
          4,
          4
        ],
        "label": "Ausgezeichnet!",
        "emoji": "⭐⭐⭐"
      },
      {
        "range": [
          3,
          3
        ],
        "label": "Sehr gut!",
        "emoji": "⭐⭐"
      },
      {
        "range": [
          2,
          2
        ],
        "label": "Gut!",
        "emoji": "⭐"
      },
      {
        "range": [
          0,
          1
        ],
        "label": "Noch üben!",
        "emoji": "📝"
      }
    ]
  }
}