{
  "theme": {
    "slug": "b2-wahlen-demokratie",
    "name": "Wahlen & Demokratie",
    "nameVi": "Bầu cử & Dân chủ",
    "nameEn": "Elections & Democracy",
    "sortOrder": 22,
    "imageUrl": "/images/themes/b2-wahlen-demokratie.png"
  },
  "words": [
    {
      "word": "Stimmzettel",
      "article": "MASKULIN",
      "plural": "die Stimmzettel",
      "wordType": "NOMEN",
      "meaningVi": "phiếu bầu",
      "meaningEn": "ballot paper",
      "exampleSentence1": "Jeder Wähler erhält einen Stimmzettel, auf dem er seine Präferenz ankreuzen kann.",
      "exampleTranslation1": "Mỗi cử tri nhận một phiếu bầu để đánh dấu lựa chọn của mình.",
      "exampleSentence2": "Ungültige Stimmzettel werden bei der Auszählung nicht berücksichtigt.",
      "exampleTranslation2": "Các phiếu bầu không hợp lệ sẽ không được tính khi kiểm phiếu.",
      "imageUrl": "/images/vocab/b2-wahlen-demokratie/der-stimmzettel.png"
    },
    {
      "word": "Wahlbeteiligung",
      "article": "FEMININ",
      "plural": "die Wahlbeteiligungen",
      "wordType": "NOMEN",
      "meaningVi": "tỷ lệ cử tri đi bầu",
      "meaningEn": "voter turnout",
      "exampleSentence1": "Eine hohe Wahlbeteiligung gilt als Zeichen einer lebendigen Demokratie.",
      "exampleTranslation1": "Tỷ lệ cử tri đi bầu cao được coi là dấu hiệu của một nền dân chủ sôi động.",
      "exampleSentence2": "Die geringe Wahlbeteiligung bei den letzten Kommunalwahlen gab Anlass zur Sorge.",
      "exampleTranslation2": "Tỷ lệ cử tri đi bầu thấp trong cuộc bầu cử địa phương vừa qua đã gây lo ngại.",
      "imageUrl": "/images/vocab/b2-wahlen-demokratie/die-wahlbeteiligung.png"
    },
    {
      "word": "Legislaturperiode",
      "article": "FEMININ",
      "plural": "die Legislaturperioden",
      "wordType": "NOMEN",
      "meaningVi": "nhiệm kỳ lập pháp/nhiệm kỳ quốc hội",
      "meaningEn": "legislative period / term (of office)",
      "exampleSentence1": "Die nächste Legislaturperiode wird voraussichtlich vier Jahre dauern.",
      "exampleTranslation1": "Nhiệm kỳ lập pháp tiếp theo dự kiến sẽ kéo dài bốn năm.",
      "exampleSentence2": "Während der gesamten Legislaturperiode müssen die Abgeordneten die Interessen ihrer Wähler vertreten.",
      "exampleTranslation2": "Trong suốt nhiệm kỳ lập pháp, các nghị sĩ phải đại diện cho lợi ích của cử tri.",
      "imageUrl": "/images/vocab/b2-wahlen-demokratie/die-legislaturperiode.png"
    },
    {
      "word": "Koalition",
      "article": "FEMININ",
      "plural": "die Koalitionen",
      "wordType": "NOMEN",
      "meaningVi": "liên minh (chính phủ)",
      "meaningEn": "coalition",
      "exampleSentence1": "Nach den Wahlen bildeten drei Parteien eine Regierungskoalition.",
      "exampleTranslation1": "Sau cuộc bầu cử, ba đảng đã thành lập một liên minh cầm quyền.",
      "exampleSentence2": "Verhandlungen über eine mögliche Koalition können Wochen in Anspruch nehmen.",
      "exampleTranslation2": "Các cuộc đàm phán về một liên minh có thể mất vài tuần.",
      "imageUrl": "/images/vocab/b2-wahlen-demokratie/die-koalition.png"
    },
    {
      "word": "Wahlkampf",
      "article": "MASKULIN",
      "plural": "die Wahlkämpfe",
      "wordType": "NOMEN",
      "meaningVi": "chiến dịch tranh cử",
      "meaningEn": "election campaign",
      "exampleSentence1": "Im hitzigen Wahlkampf versprachen die Parteien zahlreiche Reformen.",
      "exampleTranslation1": "Trong chiến dịch tranh cử sôi nổi, các đảng đã hứa hẹn nhiều cải cách.",
      "exampleSentence2": "Der Wahlkampf wird zunehmend digitaler und nutzt soziale Medien intensiv.",
      "exampleTranslation2": "Chiến dịch tranh cử ngày càng trở nên số hóa và sử dụng mạng xã hội một cách tích cực.",
      "imageUrl": "/images/vocab/b2-wahlen-demokratie/der-wahlkampf.png"
    },
    {
      "word": "Meinungsfreiheit",
      "article": "FEMININ",
      "plural": "die Meinungsfreiheiten",
      "wordType": "NOMEN",
      "meaningVi": "tự do ngôn luận",
      "meaningEn": "freedom of speech",
      "exampleSentence1": "Die Meinungsfreiheit ist ein Grundpfeiler jeder demokratischen Gesellschaft.",
      "exampleTranslation1": "Tự do ngôn luận là một trụ cột cơ bản của mọi xã hội dân chủ.",
      "exampleSentence2": "Das Recht auf Meinungsfreiheit erlaubt es Bürgern, ihre Ansichten öffentlich zu äußern, solange sie keine Gesetze verletzen.",
      "exampleTranslation2": "Quyền tự do ngôn luận cho phép công dân bày tỏ quan điểm công khai, miễn là không vi phạm pháp luật.",
      "imageUrl": "/images/vocab/b2-wahlen-demokratie/die-meinungsfreiheit.png"
    },
    {
      "word": "Grundrecht",
      "article": "NEUTRUM",
      "plural": "die Grundrechte",
      "wordType": "NOMEN",
      "meaningVi": "quyền cơ bản",
      "meaningEn": "fundamental right",
      "exampleSentence1": "Das Wahlrecht ist ein wichtiges Grundrecht, das jedem Bürger zusteht.",
      "exampleTranslation1": "Quyền bầu cử là một quyền cơ bản quan trọng mà mọi công dân đều được hưởng.",
      "exampleSentence2": "Der Schutz der Grundrechte ist Aufgabe des Staates.",
      "exampleTranslation2": "Bảo vệ các quyền cơ bản là nhiệm vụ của nhà nước.",
      "imageUrl": "/images/vocab/b2-wahlen-demokratie/das-grundrecht.png"
    },
    {
      "word": "Kandidat",
      "article": "MASKULIN",
      "plural": "die Kandidaten",
      "wordType": "NOMEN",
      "meaningVi": "ứng cử viên",
      "meaningEn": "candidate",
      "exampleSentence1": "Jeder Kandidat stellte seine politischen Ziele in einer Rede vor.",
      "exampleTranslation1": "Mỗi ứng cử viên đã trình bày các mục tiêu chính trị của mình trong một bài phát biểu.",
      "exampleSentence2": "Die Wähler konnten zwischen mehreren qualifizierten Kandidaten wählen.",
      "exampleTranslation2": "Cử tri có thể lựa chọn giữa nhiều ứng cử viên đủ tiêu chuẩn.",
      "imageUrl": "/images/vocab/b2-wahlen-demokratie/der-kandidat.png"
    },
    {
      "word": "Opposition",
      "article": "FEMININ",
      "plural": "die Oppositionen",
      "wordType": "NOMEN",
      "meaningVi": "phe đối lập",
      "meaningEn": "opposition",
      "exampleSentence1": "Die Opposition kritisierte die Regierung scharf für ihre Wirtschaftspolitik.",
      "exampleTranslation1": "Phe đối lập đã chỉ trích mạnh mẽ chính phủ về chính sách kinh tế của họ.",
      "exampleSentence2": "Eine starke Opposition ist wichtig, um die Regierung zur Rechenschaft zu ziehen.",
      "exampleTranslation2": "Một phe đối lập mạnh mẽ là quan trọng để buộc chính phủ phải chịu trách nhiệm.",
      "imageUrl": "/images/vocab/b2-wahlen-demokratie/die-opposition.png"
    },
    {
      "word": "Gewaltenteilung",
      "article": "FEMININ",
      "plural": "die Gewaltenteilungen",
      "wordType": "NOMEN",
      "meaningVi": "tam quyền phân lập",
      "meaningEn": "separation of powers",
      "exampleSentence1": "Die Gewaltenteilung sichert die Unabhängigkeit von Legislative, Exekutive und Judikative.",
      "exampleTranslation1": "Tam quyền phân lập đảm bảo sự độc lập của nhánh lập pháp, hành pháp và tư pháp.",
      "exampleSentence2": "Das Prinzip der Gewaltenteilung verhindert die Konzentration von Macht in einer Hand.",
      "exampleTranslation2": "Nguyên tắc tam quyền phân lập ngăn chặn sự tập trung quyền lực vào một tay.",
      "imageUrl": "/images/vocab/b2-wahlen-demokratie/die-gewaltenteilung.png"
    },
    {
      "word": "Wahlergebnis",
      "article": "NEUTRUM",
      "plural": "die Wahlergebnisse",
      "wordType": "NOMEN",
      "meaningVi": "kết quả bầu cử",
      "meaningEn": "election result",
      "exampleSentence1": "Das vorläufige Wahlergebnis wird noch am Wahlabend bekannt gegeben.",
      "exampleTranslation1": "Kết quả bầu cử sơ bộ sẽ được công bố ngay trong đêm bầu cử.",
      "exampleSentence2": "Das endgültige Wahlergebnis bestätigte den knappen Sieg der regierenden Partei.",
      "exampleTranslation2": "Kết quả bầu cử cuối cùng đã xác nhận chiến thắng sít sao của đảng cầm quyền.",
      "imageUrl": "/images/vocab/b2-wahlen-demokratie/das-wahlergebnis.png"
    },
    {
      "word": "Verfassung",
      "article": "FEMININ",
      "plural": "die Verfassungen",
      "wordType": "NOMEN",
      "meaningVi": "hiến pháp",
      "meaningEn": "constitution",
      "exampleSentence1": "Die Verfassung legt die grundlegenden Regeln des Staates fest.",
      "exampleTranslation1": "Hiến pháp quy định các quy tắc cơ bản của nhà nước.",
      "exampleSentence2": "Eine Änderung der Verfassung erfordert in der Regel eine Zweidrittelmehrheit.",
      "exampleTranslation2": "Việc sửa đổi hiến pháp thường yêu cầu đa số hai phần ba.",
      "imageUrl": "/images/vocab/b2-wahlen-demokratie/die-verfassung.png"
    },
    {
      "word": "Bürgerinitiative",
      "article": "FEMININ",
      "plural": "die Bürgerinitiativen",
      "wordType": "NOMEN",
      "meaningVi": "sáng kiến công dân",
      "meaningEn": "citizens' initiative",
      "exampleSentence1": "Eine Bürgerinitiative sammelte Unterschriften gegen den Bau der neuen Straße.",
      "exampleTranslation1": "Một sáng kiến công dân đã thu thập chữ ký phản đối việc xây dựng con đường mới.",
      "exampleSentence2": "Durch Bürgerinitiativen können Bürger direkt Einfluss auf politische Entscheidungen nehmen.",
      "exampleTranslation2": "Thông qua các sáng kiến công dân, người dân có thể trực tiếp tác động đến các quyết định chính trị.",
      "imageUrl": "/images/vocab/b2-wahlen-demokratie/die-buergerinitiative.png"
    },
    {
      "word": "Wählerwille",
      "article": "MASKULIN",
      "plural": "die Wählerwillen",
      "wordType": "NOMEN",
      "meaningVi": "ý chí của cử tri",
      "meaningEn": "will of the voters",
      "exampleSentence1": "Die Politiker beteuerten, den Wählerwillen respektieren zu wollen.",
      "exampleTranslation1": "Các chính trị gia khẳng định sẽ tôn trọng ý chí của cử tri.",
      "exampleSentence2": "Das Wahlsystem soll den Wählerwillen möglichst genau widerspiegeln.",
      "exampleTranslation2": "Hệ thống bầu cử nên phản ánh ý chí của cử tri một cách chính xác nhất có thể.",
      "imageUrl": "/images/vocab/b2-wahlen-demokratie/der-waehlerwille.png"
    },
    {
      "word": "Misstrauensvotum",
      "article": "NEUTRUM",
      "plural": "die Misstrauensvoten",
      "wordType": "NOMEN",
      "meaningVi": "bỏ phiếu bất tín nhiệm",
      "meaningEn": "vote of no confidence",
      "exampleSentence1": "Die Opposition kündigte ein Misstrauensvotum gegen den Regierungschef an.",
      "exampleTranslation1": "Phe đối lập đã công bố một cuộc bỏ phiếu bất tín nhiệm chống lại người đứng đầu chính phủ.",
      "exampleSentence2": "Das Misstrauensvotum scheiterte knapp, und der Ministerpräsident blieb im Amt.",
      "exampleTranslation2": "Cuộc bỏ phiếu bất tín nhiệm thất bại sít sao, và thủ tướng vẫn giữ chức.",
      "imageUrl": "/images/vocab/b2-wahlen-demokratie/das-misstrauensvotum.png"
    },
    {
      "word": "Volksabstimmung",
      "article": "FEMININ",
      "plural": "die Volksabstimmungen",
      "wordType": "NOMEN",
      "meaningVi": "trưng cầu dân ý",
      "meaningEn": "referendum",
      "exampleSentence1": "Über die umstrittene Gesetzesänderung wurde eine Volksabstimmung angesetzt.",
      "exampleTranslation1": "Một cuộc trưng cầu dân ý đã được lên lịch về việc sửa đổi luật gây tranh cãi.",
      "exampleSentence2": "Bei einer Volksabstimmung entscheidet das Volk direkt über eine Sachfrage.",
      "exampleTranslation2": "Trong một cuộc trưng cầu dân ý, người dân trực tiếp quyết định về một vấn đề cụ thể.",
      "imageUrl": "/images/vocab/b2-wahlen-demokratie/die-volksabstimmung.png"
    },
    {
      "word": "Abgeordnete",
      "article": "MASKULIN",
      "plural": "die Abgeordneten",
      "wordType": "NOMEN",
      "meaningVi": "nghị sĩ / đại biểu quốc hội",
      "meaningEn": "member of parliament / representative",
      "exampleSentence1": "Jeder Abgeordnete vertritt einen bestimmten Wahlkreis im Parlament.",
      "exampleTranslation1": "Mỗi nghị sĩ đại diện cho một khu vực bầu cử cụ thể trong quốc hội.",
      "exampleSentence2": "Die Abgeordneten debattierten stundenlang über den neuen Haushaltsentwurf.",
      "exampleTranslation2": "Các nghị sĩ đã tranh luận hàng giờ về dự thảo ngân sách mới.",
      "imageUrl": "/images/vocab/b2-wahlen-demokratie/der-abgeordnete.png"
    },
    {
      "word": "Wahlberechtigung",
      "article": "FEMININ",
      "plural": "die Wahlberechtigungen",
      "wordType": "NOMEN",
      "meaningVi": "quyền bầu cử / tư cách cử tri",
      "meaningEn": "right to vote / eligibility to vote",
      "exampleSentence1": "Die Wahlberechtigung ist an bestimmte Voraussetzungen wie Staatsbürgerschaft und Alter geknüpft.",
      "exampleTranslation1": "Quyền bầu cử gắn liền với các điều kiện nhất định như quốc tịch và độ tuổi.",
      "exampleSentence2": "Viele junge Menschen fordern eine Senkung des Wahlalters, um ihre Wahlberechtigung früher zu erhalten.",
      "exampleTranslation2": "Nhiều người trẻ yêu cầu giảm tuổi bầu cử để có quyền bầu cử sớm hơn.",
      "imageUrl": "/images/vocab/b2-wahlen-demokratie/die-wahlberechtigung.png"
    },
    {
      "word": "abstimmen",
      "article": null,
      "plural": null,
      "wordType": "VERB",
      "meaningVi": "bỏ phiếu",
      "meaningEn": "to vote, to cast a vote",
      "exampleSentence1": "Die Bürger können bei der Kommunalwahl über die Zusammensetzung des Stadtrats abstimmen.",
      "exampleTranslation1": "Công dân có thể bỏ phiếu về thành phần của hội đồng thành phố trong cuộc bầu cử địa phương.",
      "exampleSentence2": "Über den Antrag wurde im Parlament namentlich abgestimmt.",
      "exampleTranslation2": "Đề xuất đã được bỏ phiếu theo tên trong quốc hội.",
      "imageUrl": "/images/vocab/b2-wahlen-demokratie/abstimmen.png"
    },
    {
      "word": "sich enthalten",
      "article": null,
      "plural": null,
      "wordType": "VERB",
      "meaningVi": "bỏ phiếu trắng / kiêng cử",
      "meaningEn": "to abstain",
      "exampleSentence1": "Einige Abgeordnete enthielten sich bei der Abstimmung, um ihre Neutralität zu wahren.",
      "exampleTranslation1": "Một số nghị sĩ đã bỏ phiếu trắng để duy trì sự trung lập của họ.",
      "exampleSentence2": "Es ist wichtig, sich nicht zu enthalten, wenn man eine starke Meinung zu einem Thema hat.",
      "exampleTranslation2": "Điều quan trọng là không nên bỏ phiếu trắng nếu bạn có quan điểm mạnh mẽ về một vấn đề.",
      "imageUrl": "/images/vocab/b2-wahlen-demokratie/sich-enthalten.png"
    },
    {
      "word": "regieren",
      "article": null,
      "plural": null,
      "wordType": "VERB",
      "meaningVi": "cầm quyền / quản lý",
      "meaningEn": "to govern",
      "exampleSentence1": "Die neu gewählte Partei wird das Land für die nächsten vier Jahre regieren.",
      "exampleTranslation1": "Đảng mới đắc cử sẽ điều hành đất nước trong bốn năm tới.",
      "exampleSentence2": "Effektiv zu regieren bedeutet, die Interessen aller Bürger zu berücksichtigen.",
      "exampleTranslation2": "Quản lý hiệu quả có nghĩa là xem xét lợi ích của tất cả công dân.",
      "imageUrl": "/images/vocab/b2-wahlen-demokratie/regieren.png"
    },
    {
      "word": "verabschieden",
      "article": null,
      "plural": null,
      "wordType": "VERB",
      "meaningVi": "thông qua (luật) / ban hành",
      "meaningEn": "to pass/adopt (a law)",
      "exampleSentence1": "Das Parlament muss das neue Gesetz noch vor der Sommerpause verabschieden.",
      "exampleTranslation1": "Quốc hội phải thông qua luật mới trước kỳ nghỉ hè.",
      "exampleSentence2": "Die Regierung hat ein Paket von Maßnahmen zur Stärkung der Wirtschaft verabschiedet.",
      "exampleTranslation2": "Chính phủ đã thông qua một gói các biện pháp để tăng cường nền kinh tế.",
      "imageUrl": "/images/vocab/b2-wahlen-demokratie/verabschieden.png"
    },
    {
      "word": "kandidieren",
      "article": null,
      "plural": null,
      "wordType": "VERB",
      "meaningVi": "ứng cử",
      "meaningEn": "to run for office",
      "exampleSentence1": "Sie hat angekündigt, bei den nächsten Präsidentschaftswahlen zu kandidieren.",
      "exampleTranslation1": "Cô ấy đã thông báo sẽ ứng cử trong cuộc bầu cử tổng thống tiếp theo.",
      "exampleSentence2": "Um erfolgreich zu kandidieren, braucht man ein überzeugendes Programm und viel Unterstützung.",
      "exampleTranslation2": "Để ứng cử thành công, cần có một chương trình thuyết phục và nhiều sự ủng hộ.",
      "imageUrl": "/images/vocab/b2-wahlen-demokratie/kandidieren.png"
    },
    {
      "word": "protestieren",
      "article": null,
      "plural": null,
      "wordType": "VERB",
      "meaningVi": "biểu tình / phản đối",
      "meaningEn": "to protest",
      "exampleSentence1": "Tausende Menschen protestierten friedlich gegen die geplante Rentenreform.",
      "exampleTranslation1": "Hàng ngàn người đã biểu tình ôn hòa chống lại cải cách lương hưu dự kiến.",
      "exampleSentence2": "Die Studenten protestierten gegen die Erhöhung der Studiengebühren.",
      "exampleTranslation2": "Sinh viên đã phản đối việc tăng học phí.",
      "imageUrl": "/images/vocab/b2-wahlen-demokratie/protestieren.png"
    },
    {
      "word": "beeinflussen",
      "article": null,
      "plural": null,
      "wordType": "VERB",
      "meaningVi": "ảnh hưởng",
      "meaningEn": "to influence",
      "exampleSentence1": "Medien können die öffentliche Meinung und somit Wahlergebnisse stark beeinflussen.",
      "exampleTranslation1": "Truyền thông có thể ảnh hưởng mạnh mẽ đến dư luận và do đó là kết quả bầu cử.",
      "exampleSentence2": "Lobbyisten versuchen oft, politische Entscheidungen zu ihren Gunsten zu beeinflussen.",
      "exampleTranslation2": "Các nhà vận động hành lang thường cố gắng ảnh hưởng đến các quyết định chính trị theo hướng có lợi cho họ.",
      "imageUrl": "/images/vocab/b2-wahlen-demokratie/beeinflussen.png"
    },
    {
      "word": "sich einsetzen für",
      "article": null,
      "plural": null,
      "wordType": "VERB",
      "meaningVi": "ủng hộ / đấu tranh cho",
      "meaningEn": "to advocate for, to stand up for",
      "exampleSentence1": "Sie setzt sich seit Jahren für mehr Umweltschutz in der Politik ein.",
      "exampleTranslation1": "Cô ấy đã đấu tranh nhiều năm cho việc bảo vệ môi trường nhiều hơn trong chính trị.",
      "exampleSentence2": "Als Abgeordneter muss man sich für die Anliegen seiner Wähler einsetzen.",
      "exampleTranslation2": "Với tư cách là một nghị sĩ, người ta phải đấu tranh cho những mối quan tâm của cử tri mình.",
      "imageUrl": "/images/vocab/b2-wahlen-demokratie/sich-einsetzen-fuer.png"
    },
    {
      "word": "legitimieren",
      "article": null,
      "plural": null,
      "wordType": "VERB",
      "meaningVi": "hợp pháp hóa / xác nhận tính hợp pháp",
      "meaningEn": "to legitimize",
      "exampleSentence1": "Durch freie und faire Wahlen legitimiert sich eine Regierung.",
      "exampleTranslation1": "Một chính phủ tự hợp pháp hóa thông qua các cuộc bầu cử tự do và công bằng.",
      "exampleSentence2": "Es ist entscheidend, dass die Entscheidungen des Parlaments durch den Volkswillen legitimiert sind.",
      "exampleTranslation2": "Điều quan trọng là các quyết định của quốc hội phải được hợp pháp hóa bởi ý chí của nhân dân.",
      "imageUrl": "/images/vocab/b2-wahlen-demokratie/legitimieren.png"
    },
    {
      "word": "demokratisch",
      "article": null,
      "plural": null,
      "wordType": "ADJEKTIV",
      "meaningVi": "dân chủ",
      "meaningEn": "democratic",
      "exampleSentence1": "Eine demokratische Gesellschaft basiert auf den Prinzipien der Gleichheit und Freiheit.",
      "exampleTranslation1": "Một xã hội dân chủ dựa trên các nguyên tắc bình đẳng và tự do.",
      "exampleSentence2": "Die demokratischen Institutionen müssen gestärkt werden, um die Stabilität des Landes zu gewährleisten.",
      "exampleTranslation2": "Các thể chế dân chủ phải được tăng cường để đảm bảo sự ổn định của đất nước.",
      "imageUrl": "/images/vocab/b2-wahlen-demokratie/demokratisch.png"
    },
    {
      "word": "umstritten",
      "article": null,
      "plural": null,
      "wordType": "ADJEKTIV",
      "meaningVi": "gây tranh cãi",
      "meaningEn": "controversial",
      "exampleSentence1": "Die umstrittene Gesetzesvorlage führte zu heftigen Debatten im Parlament.",
      "exampleTranslation1": "Dự luật gây tranh cãi đã dẫn đến các cuộc tranh luận gay gắt trong quốc hội.",
      "exampleSentence2": "Es gibt viele umstrittene Themen, die die öffentliche Meinung spalten.",
      "exampleTranslation2": "Có nhiều vấn đề gây tranh cãi chia rẽ dư luận.",
      "imageUrl": "/images/vocab/b2-wahlen-demokratie/umstritten.png"
    },
    {
      "word": "mehrheitlich",
      "article": null,
      "plural": null,
      "wordType": "ADJEKTIV",
      "meaningVi": "đa số / theo đa số",
      "meaningEn": "by majority",
      "exampleSentence1": "Der Antrag wurde mehrheitlich angenommen, obwohl es einige Gegenstimmen gab.",
      "exampleTranslation1": "Đề xuất đã được thông qua theo đa số, mặc dù có một số phiếu chống.",
      "exampleSentence2": "Die Entscheidungen im Stadtrat werden oft mehrheitlich getroffen.",
      "exampleTranslation2": "Các quyết định trong hội đồng thành phố thường được đưa ra theo đa số.",
      "imageUrl": "/images/vocab/b2-wahlen-demokratie/mehrheitlich.png"
    },
    {
      "word": "parteiübergreifend",
      "article": null,
      "plural": null,
      "wordType": "ADJEKTIV",
      "meaningVi": "liên đảng / xuyên đảng",
      "meaningEn": "cross-party",
      "exampleSentence1": "Es gab eine parteiübergreifende Einigung über die Notwendigkeit der Reform.",
      "exampleTranslation1": "Đã có một sự đồng thuận liên đảng về sự cần thiết của cải cách.",
      "exampleSentence2": "Parteiübergreifende Zusammenarbeit ist entscheidend, um komplexe Probleme zu lösen.",
      "exampleTranslation2": "Hợp tác liên đảng là rất quan trọng để giải quyết các vấn đề phức tạp.",
      "imageUrl": "/images/vocab/b2-wahlen-demokratie/parteiuebergreifend.png"
    },
    {
      "word": "verfassungswidrig",
      "article": null,
      "plural": null,
      "wordType": "ADJEKTIV",
      "meaningVi": "vi hiến",
      "meaningEn": "unconstitutional",
      "exampleSentence1": "Das Gericht erklärte das Gesetz für verfassungswidrig.",
      "exampleTranslation1": "Tòa án tuyên bố luật đó là vi hiến.",
      "exampleSentence2": "Eine Maßnahme, die gegen die Grundrechte verstößt, ist verfassungswidrig.",
      "exampleTranslation2": "Một biện pháp vi phạm các quyền cơ bản là vi hiến.",
      "imageUrl": "/images/vocab/b2-wahlen-demokratie/verfassungswidrig.png"
    },
    {
      "word": "repräsentativ",
      "article": null,
      "plural": null,
      "wordType": "ADJEKTIV",
      "meaningVi": "đại diện / mang tính đại diện",
      "meaningEn": "representative",
      "exampleSentence1": "Um repräsentative Ergebnisse zu erzielen, wurde eine Umfrage unter 1000 Bürgern durchgeführt.",
      "exampleTranslation1": "Để đạt được kết quả mang tính đại diện, một cuộc khảo sát đã được thực hiện với 1000 công dân.",
      "exampleSentence2": "Das Parlament sollte die Vielfalt der Gesellschaft repräsentativ abbilden.",
      "exampleTranslation2": "Quốc hội nên phản ánh sự đa dạng của xã hội một cách đại diện.",
      "imageUrl": "/images/vocab/b2-wahlen-demokratie/repraesentativ.png"
    },
    {
      "word": "transparent",
      "article": null,
      "plural": null,
      "wordType": "ADJEKTIV",
      "meaningVi": "minh bạch",
      "meaningEn": "transparent",
      "exampleSentence1": "Eine transparente Regierung fördert das Vertrauen der Bürger in die Politik.",
      "exampleTranslation1": "Một chính phủ minh bạch thúc đẩy niềm tin của công dân vào chính trị.",
      "exampleSentence2": "Der Prozess der Entscheidungsfindung muss transparent sein, um Korruption vorzubeugen.",
      "exampleTranslation2": "Quá trình ra quyết định phải minh bạch để ngăn chặn tham nhũng.",
      "imageUrl": "/images/vocab/b2-wahlen-demokratie/transparent.png"
    },
    {
      "word": "einstimmig",
      "article": null,
      "plural": null,
      "wordType": "ADVERB",
      "meaningVi": "nhất trí / đồng lòng",
      "meaningEn": "unanimously",
      "exampleSentence1": "Der Beschluss wurde vom Ausschuss einstimmig gefasst.",
      "exampleTranslation1": "Quyết định đã được ủy ban thông qua nhất trí.",
      "exampleSentence2": "In einer idealen Demokratie sollten wichtige Entscheidungen möglichst einstimmig getroffen werden.",
      "exampleTranslation2": "Trong một nền dân chủ lý tưởng, các quyết định quan trọng nên được đưa ra một cách nhất trí càng nhiều càng tốt.",
      "imageUrl": "/images/vocab/b2-wahlen-demokratie/einstimmig.png"
    }
  ]
}
