{
  "id": "L-A2-GOETHE-005-T2",
  "level": "A2",
  "teil": 2,
  "teil_name": "Zusammenhängendes Gespräch",
  "task_type": "mc_abc",
  "topic": "Beim Arzt Symptome beschreiben",
  "audio_file": "/audio/listening/A2/Teil2-Zusammenhaengendes-Gespraech/L-A2-GOETHE-005-T2.mp3",
  "metadata": {
    "generated_at": "2026-03-19T10:04:11.116126",
    "version": 2,
    "gespraech_count": 6,
    "source_script": "data/scripts/A2/Teil2-Zusammenhaengendes-Gespraech/L-A2-GOETHE-005-T2.json",
    "regenerated_at": "2026-03-20T07:45:14.473Z"
  },
  "questions": [
    {
      "id": "Q1",
      "gespraech": 1,
      "type": "mc_abc",
      "question": "Worum geht es im Gespräch 1?",
      "options": {
        "a": "Wohnung und Haushalt",
        "b": "Einkaufen und Geld",
        "c": "Arbeit und Beruf"
      },
      "answer": "c",
      "points": 1,
      "explanation": {
        "de": "Man hört: \"Arbeit und Beruf\".",
        "vi": "",
        "key_evidence": "Arbeit und Beruf",
        "key_vocabulary": []
      }
    },
    {
      "id": "Q2",
      "gespraech": 1,
      "type": "mc_abc",
      "question": "Wie heißt eine Person im Gespräch 1?",
      "options": {
        "a": "Anna",
        "b": "Doktor",
        "c": "Sabine"
      },
      "answer": "b",
      "points": 1,
      "explanation": {
        "de": "Man hört: \"Doktor\".",
        "vi": "",
        "key_evidence": "Doktor",
        "key_vocabulary": [
          {
            "w": "heißen",
            "m": "to be called"
          }
        ]
      }
    },
    {
      "id": "Q3",
      "gespraech": 1,
      "type": "mc_abc",
      "question": "Woher kommt die Person (Gespräch 1)?",
      "options": {
        "a": "Hals",
        "b": "Düsseldorf",
        "c": "Bremen"
      },
      "answer": "a",
      "points": 1,
      "explanation": {
        "de": "Man hört: \"Hals\".",
        "vi": "",
        "key_evidence": "Hals",
        "key_vocabulary": [
          {
            "w": "kommen aus",
            "m": "to come from"
          }
        ]
      }
    }
  ],
  "scoring": {
    "total_points": 3,
    "pass_threshold": 2,
    "grading": [
      {
        "range": [
          3,
          3
        ],
        "label": "Ausgezeichnet!",
        "emoji": "⭐⭐⭐"
      },
      {
        "range": [
          3,
          3
        ],
        "label": "Sehr gut!",
        "emoji": "⭐⭐"
      },
      {
        "range": [
          2,
          2
        ],
        "label": "Gut!",
        "emoji": "⭐"
      },
      {
        "range": [
          0,
          1
        ],
        "label": "Noch üben!",
        "emoji": "📝"
      }
    ]
  }
}